long_utils/__init__.py
long_utils/image/__init__.py
long_utils/image/search.py
long_utils/zlog/__init__.py
long_utils/zlog/enum/__init__.py
long_utils/zlog/log.py
long_utils-1.0.0.dist-info/entry_points.txt
long_utils-1.0.0.dist-info/LICENSE
long_utils-1.0.0.dist-info/METADATA
long_utils-1.0.0.dist-info/WHEEL
long_utils-1.0.0.dist-info/RECORD
