Metadata-Version: 2.1
Name: long-utils
Version: 1.0.0
Summary: 一款自行使用的工具库
Author: 往事
Author-email: 82131529@qq.com
Requires-Python: >=3.7,<4.0
Classifier: Programming Language :: Python :: 3
Classifier: Programming Language :: Python :: 3.7
Classifier: Programming Language :: Python :: 3.8
Classifier: Programming Language :: Python :: 3.9
Classifier: Programming Language :: Python :: 3.10
Classifier: Programming Language :: Python :: 3.11
Requires-Dist: opencv-python (>=4.8.1.78,<5.0.0.0)
